Products.MeetingCommunes-4.2.16-py3.12-nspkg.pth
Products/MeetingCommunes/README.txt
Products/MeetingCommunes/__init__.py
Products/MeetingCommunes/adapters.py
Products/MeetingCommunes/config.py
Products/MeetingCommunes/configure.zcml
Products/MeetingCommunes/interfaces.py
Products/MeetingCommunes/overrides.zcml
Products/MeetingCommunes/profiles.zcml
Products/MeetingCommunes/refresh.txt
Products/MeetingCommunes/setuphandlers.py
Products/MeetingCommunes/testing.py
Products/MeetingCommunes/testing.zcml
Products/MeetingCommunes/utils.py
Products/MeetingCommunes/version.txt
Products/MeetingCommunes/Extensions/ImportCategories.ods
Products/MeetingCommunes/Extensions/__init__.py
Products/MeetingCommunes/Extensions/add_portal_configuration.py
Products/MeetingCommunes/Extensions/force-docgen-column_modifier.py
Products/MeetingCommunes/Extensions/force-language.py
Products/MeetingCommunes/Extensions/import-csv-inforius.py
Products/MeetingCommunes/Extensions/importGroups.ods
Products/MeetingCommunes/Extensions/importGroupsUsersAndRoles.ods
Products/MeetingCommunes/Extensions/initialize-gp-with-in-charge.py
Products/MeetingCommunes/Extensions/utils.py
Products/MeetingCommunes/browser/__init__.py
Products/MeetingCommunes/browser/configure.zcml
Products/MeetingCommunes/browser/overrides.py
Products/MeetingCommunes/locales/PloneMeeting.pot
Products/MeetingCommunes/locales/imio.actionspanel.pot
Products/MeetingCommunes/locales/imio.history.pot
Products/MeetingCommunes/locales/plone.pot
Products/MeetingCommunes/locales/sync_pos.sh
Products/MeetingCommunes/locales/de/LC_MESSAGES/PloneMeeting.po
Products/MeetingCommunes/locales/de/LC_MESSAGES/imio.actionspanel.po
Products/MeetingCommunes/locales/de/LC_MESSAGES/imio.history.po
Products/MeetingCommunes/locales/de/LC_MESSAGES/plone.po
Products/MeetingCommunes/locales/en/LC_MESSAGES/PloneMeeting.po
Products/MeetingCommunes/locales/en/LC_MESSAGES/imio.actionspanel.po
Products/MeetingCommunes/locales/en/LC_MESSAGES/imio.history.po
products_meetingcommunes-4.2.16.dist-info/METADATA
products_meetingcommunes-4.2.16.dist-info/WHEEL
products_meetingcommunes-4.2.16.dist-info/namespace_packages.txt
products_meetingcommunes-4.2.16.dist-info/top_level.txt
products_meetingcommunes-4.2.16.dist-info/RECORD
